big_loader/__init__.py
big_loader/pipelines.py
big_loader-0.0.0.dist-info/METADATA
big_loader-0.0.0.dist-info/WHEEL
big_loader-0.0.0.dist-info/top_level.txt
big_loader-0.0.0.dist-info/RECORD
